LICENSE.txt
README.md
setup.cfg
setup.py
aluratemp/__init__.py
aluratemp/aluratemp.py
aluratemp_matheusnascimento.egg-info/PKG-INFO
aluratemp_matheusnascimento.egg-info/SOURCES.txt
aluratemp_matheusnascimento.egg-info/dependency_links.txt
aluratemp_matheusnascimento.egg-info/top_level.txt