Metadata-Version: 2.4
Name: aluratemp-matheusnascimento
Version: 1.0.0
Summary: Um simples conversor de temperatura (Celsius - Fahrenheit)
Home-page: https://github.com/yanorestes/aluratemp
Author: Matheus Nascimento
Author-email: matheus.maciel34@gmail.com
License: MIT
Project-URL: Código fonte, https://github.com/yanorestes/aluratemp
Project-URL: Download, https://github.com/yanorestes/aluratemp/archive/1.0.0.zip
Keywords: conversor temperatura aluraclassifiers = [
License-File: LICENSE.txt
Dynamic: author
Dynamic: author-email
Dynamic: description
Dynamic: home-page
Dynamic: keywords
Dynamic: license
Dynamic: license-file
Dynamic: project-url
Dynamic: summary
